Metadata-Version: 2.1
Name: conan-index-tools
Version: 0.0.8.dev0
Summary: conan_index_tool is a tool for helping contributing Conan recipes in theconan center index repository
Home-page: https://conan.io
Author: JFrog LTD
Author-email: luism@jfrog.com
License: MIT
Keywords: C/C++,package,libraries,developer,manager,dependency,tool,c,c++,cpp
Platform: UNKNOWN
Classifier: Development Status :: 5 - Production/Stable
Classifier: Intended Audience :: Developers
Classifier: Topic :: Software Development :: Build Tools
Classifier: License :: OSI Approved :: MIT License
Classifier: Programming Language :: Python :: 2
Classifier: Programming Language :: Python :: 2.7
Classifier: Programming Language :: Python :: 3
Classifier: Programming Language :: Python :: 3.6
